[{"id":131,"name":"Force atack","startDate":{"year":2022,"month":"SEPTEMBER","dayOfMonth":9,"dayOfWeek":"FRIDAY","era":"CE","dayOfYear":252,"leapYear":false,"monthValue":9,"chronology":{"id":"ISO","calendarType":"iso8601"}},"endDate":{"year":2023,"month":"AUGUST","dayOfMonth":8,"dayOfWeek":"TUESDAY","era":"CE","dayOfYear":220,"leapYear":false,"monthValue":8,"chronology":{"id":"ISO","calendarType":"iso8601"}},"distance":164378,"assignedSpaceship":null,"assignedCrew":null,"missionResult":"PLANNED"}]